{
  "@context": "http://iiif.io/api/presentation/3/context.json",
  "id": "https://tanyaclement.github.io/harvard1953/annotations/august-4-afternoon-part-three-canvas-1-audience.json",
  "type": "AnnotationPage",
  "label": "Audience",
  "items": [
    {
      "@context": "http://www.w3.org/ns/anno.jsonld",
      "id": "august-4-afternoon-part-three-canvas-1-audience-annotation-0.json",
      "type": "Annotation",
      "motivation": [
        "supplementing",
        "commenting"
      ],
      "body": [
        {
          "type": "TextualBody",
          "value": " LAUGHTER",
          "format": "text/plain",
          "purpose": "commenting"
        },
        {
          "type": "TextualBody",
          "value": "Audience",
          "format": "text/plain",
          "purpose": "tagging"
        },
        {
          "type": "TextualBody",
          "value": "Session Discussion August 4",
          "format": "text/plain",
          "purpose": "tagging"
        }
      ],
      "target": {
        "source": "https://tanyaclement.github.io/harvard1953/august-4-afternoon-part-three/canvas-1/canvas",
        "selector": {
          "type": "PointSelector",
          "t": "0.0"
        }
      }
    },
    {
      "@context": "http://www.w3.org/ns/anno.jsonld",
      "id": "august-4-afternoon-part-three-canvas-1-audience-annotation-1.json",
      "type": "Annotation",
      "motivation": [
        "supplementing",
        "commenting"
      ],
      "body": [
        {
          "type": "TextualBody",
          "value": " Why is it it varies from book to book and from reader to reader. But I do think that there are very many people today who simply can't read Sinclair Lewis. They just find him intolerably stupid.",
          "format": "text/plain",
          "purpose": "commenting"
        },
        {
          "type": "TextualBody",
          "value": "Audience",
          "format": "text/plain",
          "purpose": "tagging"
        },
        {
          "type": "TextualBody",
          "value": "Session Discussion August 4",
          "format": "text/plain",
          "purpose": "tagging"
        }
      ],
      "target": {
        "source": "https://tanyaclement.github.io/harvard1953/august-4-afternoon-part-three/canvas-1/canvas",
        "selector": {
          "type": "PointSelector",
          "t": "40.0"
        }
      }
    },
    {
      "@context": "http://www.w3.org/ns/anno.jsonld",
      "id": "august-4-afternoon-part-three-canvas-1-audience-annotation-2.json",
      "type": "Annotation",
      "motivation": [
        "supplementing",
        "commenting"
      ],
      "body": [
        {
          "type": "TextualBody",
          "value": " LAUGHTER",
          "format": "text/plain",
          "purpose": "commenting"
        },
        {
          "type": "TextualBody",
          "value": "Audience",
          "format": "text/plain",
          "purpose": "tagging"
        },
        {
          "type": "TextualBody",
          "value": "Session Discussion August 4",
          "format": "text/plain",
          "purpose": "tagging"
        }
      ],
      "target": {
        "source": "https://tanyaclement.github.io/harvard1953/august-4-afternoon-part-three/canvas-1/canvas",
        "selector": {
          "type": "PointSelector",
          "t": "63.0"
        }
      }
    },
    {
      "@context": "http://www.w3.org/ns/anno.jsonld",
      "id": "august-4-afternoon-part-three-canvas-1-audience-annotation-3.json",
      "type": "Annotation",
      "motivation": [
        "supplementing",
        "commenting"
      ],
      "body": [
        {
          "type": "TextualBody",
          "value": " LAUGHTER",
          "format": "text/plain",
          "purpose": "commenting"
        },
        {
          "type": "TextualBody",
          "value": "Audience",
          "format": "text/plain",
          "purpose": "tagging"
        },
        {
          "type": "TextualBody",
          "value": "Session Discussion August 4",
          "format": "text/plain",
          "purpose": "tagging"
        }
      ],
      "target": {
        "source": "https://tanyaclement.github.io/harvard1953/august-4-afternoon-part-three/canvas-1/canvas",
        "selector": {
          "type": "PointSelector",
          "t": "86.0"
        }
      }
    },
    {
      "@context": "http://www.w3.org/ns/anno.jsonld",
      "id": "august-4-afternoon-part-three-canvas-1-audience-annotation-4.json",
      "type": "Annotation",
      "motivation": [
        "supplementing",
        "commenting"
      ],
      "body": [
        {
          "type": "TextualBody",
          "value": " LAUGHTER",
          "format": "text/plain",
          "purpose": "commenting"
        },
        {
          "type": "TextualBody",
          "value": "Audience",
          "format": "text/plain",
          "purpose": "tagging"
        },
        {
          "type": "TextualBody",
          "value": "Session Discussion August 4",
          "format": "text/plain",
          "purpose": "tagging"
        }
      ],
      "target": {
        "source": "https://tanyaclement.github.io/harvard1953/august-4-afternoon-part-three/canvas-1/canvas",
        "selector": {
          "type": "PointSelector",
          "t": "271.0"
        }
      }
    },
    {
      "@context": "http://www.w3.org/ns/anno.jsonld",
      "id": "august-4-afternoon-part-three-canvas-1-audience-annotation-5.json",
      "type": "Annotation",
      "motivation": [
        "supplementing",
        "commenting"
      ],
      "body": [
        {
          "type": "TextualBody",
          "value": " INAUDIBLE  come down to Earth. I dare ask a question. A very distinguished professor emeritus of Harvard has said that, \"William Faulkner writes for morons,\" unquote. May we have some expert comment on that?",
          "format": "text/plain",
          "purpose": "commenting"
        },
        {
          "type": "TextualBody",
          "value": "Audience",
          "format": "text/plain",
          "purpose": "tagging"
        },
        {
          "type": "TextualBody",
          "value": "Session Discussion August 4",
          "format": "text/plain",
          "purpose": "tagging"
        }
      ],
      "target": {
        "source": "https://tanyaclement.github.io/harvard1953/august-4-afternoon-part-three/canvas-1/canvas",
        "selector": {
          "type": "PointSelector",
          "t": "346.0"
        }
      }
    },
    {
      "@context": "http://www.w3.org/ns/anno.jsonld",
      "id": "august-4-afternoon-part-three-canvas-1-audience-annotation-6.json",
      "type": "Annotation",
      "motivation": [
        "supplementing",
        "commenting"
      ],
      "body": [
        {
          "type": "TextualBody",
          "value": " LAUGHTER",
          "format": "text/plain",
          "purpose": "commenting"
        },
        {
          "type": "TextualBody",
          "value": "Audience",
          "format": "text/plain",
          "purpose": "tagging"
        },
        {
          "type": "TextualBody",
          "value": "Session Discussion August 4",
          "format": "text/plain",
          "purpose": "tagging"
        }
      ],
      "target": {
        "source": "https://tanyaclement.github.io/harvard1953/august-4-afternoon-part-three/canvas-1/canvas",
        "selector": {
          "type": "PointSelector",
          "t": "365.0"
        }
      }
    },
    {
      "@context": "http://www.w3.org/ns/anno.jsonld",
      "id": "august-4-afternoon-part-three-canvas-1-audience-annotation-7.json",
      "type": "Annotation",
      "motivation": [
        "supplementing",
        "commenting"
      ],
      "body": [
        {
          "type": "TextualBody",
          "value": " LAUGHTER",
          "format": "text/plain",
          "purpose": "commenting"
        },
        {
          "type": "TextualBody",
          "value": "Audience",
          "format": "text/plain",
          "purpose": "tagging"
        },
        {
          "type": "TextualBody",
          "value": "Session Discussion August 4",
          "format": "text/plain",
          "purpose": "tagging"
        }
      ],
      "target": {
        "source": "https://tanyaclement.github.io/harvard1953/august-4-afternoon-part-three/canvas-1/canvas",
        "selector": {
          "type": "PointSelector",
          "t": "376.0"
        }
      }
    },
    {
      "@context": "http://www.w3.org/ns/anno.jsonld",
      "id": "august-4-afternoon-part-three-canvas-1-audience-annotation-8.json",
      "type": "Annotation",
      "motivation": [
        "supplementing",
        "commenting"
      ],
      "body": [
        {
          "type": "TextualBody",
          "value": " CLAPPING",
          "format": "text/plain",
          "purpose": "commenting"
        },
        {
          "type": "TextualBody",
          "value": "Audience",
          "format": "text/plain",
          "purpose": "tagging"
        },
        {
          "type": "TextualBody",
          "value": "Session Discussion August 4",
          "format": "text/plain",
          "purpose": "tagging"
        }
      ],
      "target": {
        "source": "https://tanyaclement.github.io/harvard1953/august-4-afternoon-part-three/canvas-1/canvas",
        "selector": {
          "type": "PointSelector",
          "t": "378.0"
        }
      }
    },
    {
      "@context": "http://www.w3.org/ns/anno.jsonld",
      "id": "august-4-afternoon-part-three-canvas-1-audience-annotation-9.json",
      "type": "Annotation",
      "motivation": [
        "supplementing",
        "commenting"
      ],
      "body": [
        {
          "type": "TextualBody",
          "value": " LAUGHTER",
          "format": "text/plain",
          "purpose": "commenting"
        },
        {
          "type": "TextualBody",
          "value": "Audience",
          "format": "text/plain",
          "purpose": "tagging"
        },
        {
          "type": "TextualBody",
          "value": "Session Discussion August 4",
          "format": "text/plain",
          "purpose": "tagging"
        }
      ],
      "target": {
        "source": "https://tanyaclement.github.io/harvard1953/august-4-afternoon-part-three/canvas-1/canvas",
        "selector": {
          "type": "PointSelector",
          "t": "401.0"
        }
      }
    },
    {
      "@context": "http://www.w3.org/ns/anno.jsonld",
      "id": "august-4-afternoon-part-three-canvas-1-audience-annotation-10.json",
      "type": "Annotation",
      "motivation": [
        "supplementing",
        "commenting"
      ],
      "body": [
        {
          "type": "TextualBody",
          "value": " INAUDIBLE",
          "format": "text/plain",
          "purpose": "commenting"
        },
        {
          "type": "TextualBody",
          "value": "Audience",
          "format": "text/plain",
          "purpose": "tagging"
        },
        {
          "type": "TextualBody",
          "value": "Session Discussion August 4",
          "format": "text/plain",
          "purpose": "tagging"
        }
      ],
      "target": {
        "source": "https://tanyaclement.github.io/harvard1953/august-4-afternoon-part-three/canvas-1/canvas",
        "selector": {
          "type": "PointSelector",
          "t": "406.0"
        }
      }
    },
    {
      "@context": "http://www.w3.org/ns/anno.jsonld",
      "id": "august-4-afternoon-part-three-canvas-1-audience-annotation-11.json",
      "type": "Annotation",
      "motivation": [
        "supplementing",
        "commenting"
      ],
      "body": [
        {
          "type": "TextualBody",
          "value": " LAUGHTER",
          "format": "text/plain",
          "purpose": "commenting"
        },
        {
          "type": "TextualBody",
          "value": "Audience",
          "format": "text/plain",
          "purpose": "tagging"
        },
        {
          "type": "TextualBody",
          "value": "Session Discussion August 4",
          "format": "text/plain",
          "purpose": "tagging"
        }
      ],
      "target": {
        "source": "https://tanyaclement.github.io/harvard1953/august-4-afternoon-part-three/canvas-1/canvas",
        "selector": {
          "type": "PointSelector",
          "t": "447.0"
        }
      }
    },
    {
      "@context": "http://www.w3.org/ns/anno.jsonld",
      "id": "august-4-afternoon-part-three-canvas-1-audience-annotation-12.json",
      "type": "Annotation",
      "motivation": [
        "supplementing",
        "commenting"
      ],
      "body": [
        {
          "type": "TextualBody",
          "value": " CHUCKLING",
          "format": "text/plain",
          "purpose": "commenting"
        },
        {
          "type": "TextualBody",
          "value": "Audience",
          "format": "text/plain",
          "purpose": "tagging"
        },
        {
          "type": "TextualBody",
          "value": "Session Discussion August 4",
          "format": "text/plain",
          "purpose": "tagging"
        }
      ],
      "target": {
        "source": "https://tanyaclement.github.io/harvard1953/august-4-afternoon-part-three/canvas-1/canvas",
        "selector": {
          "type": "PointSelector",
          "t": "1102.0"
        }
      }
    },
    {
      "@context": "http://www.w3.org/ns/anno.jsonld",
      "id": "august-4-afternoon-part-three-canvas-1-audience-annotation-13.json",
      "type": "Annotation",
      "motivation": [
        "supplementing",
        "commenting"
      ],
      "body": [
        {
          "type": "TextualBody",
          "value": " CHUCKLING",
          "format": "text/plain",
          "purpose": "commenting"
        },
        {
          "type": "TextualBody",
          "value": "Audience",
          "format": "text/plain",
          "purpose": "tagging"
        },
        {
          "type": "TextualBody",
          "value": "Session Discussion August 4",
          "format": "text/plain",
          "purpose": "tagging"
        }
      ],
      "target": {
        "source": "https://tanyaclement.github.io/harvard1953/august-4-afternoon-part-three/canvas-1/canvas",
        "selector": {
          "type": "PointSelector",
          "t": "1340.0"
        }
      }
    },
    {
      "@context": "http://www.w3.org/ns/anno.jsonld",
      "id": "august-4-afternoon-part-three-canvas-1-audience-annotation-14.json",
      "type": "Annotation",
      "motivation": [
        "supplementing",
        "commenting"
      ],
      "body": [
        {
          "type": "TextualBody",
          "value": " CHUCKLING",
          "format": "text/plain",
          "purpose": "commenting"
        },
        {
          "type": "TextualBody",
          "value": "Audience",
          "format": "text/plain",
          "purpose": "tagging"
        },
        {
          "type": "TextualBody",
          "value": "Session Discussion August 4",
          "format": "text/plain",
          "purpose": "tagging"
        }
      ],
      "target": {
        "source": "https://tanyaclement.github.io/harvard1953/august-4-afternoon-part-three/canvas-1/canvas",
        "selector": {
          "type": "PointSelector",
          "t": "1428.0"
        }
      }
    },
    {
      "@context": "http://www.w3.org/ns/anno.jsonld",
      "id": "august-4-afternoon-part-three-canvas-1-audience-annotation-15.json",
      "type": "Annotation",
      "motivation": [
        "supplementing",
        "commenting"
      ],
      "body": [
        {
          "type": "TextualBody",
          "value": " CHUCKLING",
          "format": "text/plain",
          "purpose": "commenting"
        },
        {
          "type": "TextualBody",
          "value": "Audience",
          "format": "text/plain",
          "purpose": "tagging"
        },
        {
          "type": "TextualBody",
          "value": "Session Discussion August 4",
          "format": "text/plain",
          "purpose": "tagging"
        }
      ],
      "target": {
        "source": "https://tanyaclement.github.io/harvard1953/august-4-afternoon-part-three/canvas-1/canvas",
        "selector": {
          "type": "PointSelector",
          "t": "1559.0"
        }
      }
    },
    {
      "@context": "http://www.w3.org/ns/anno.jsonld",
      "id": "august-4-afternoon-part-three-canvas-1-audience-annotation-16.json",
      "type": "Annotation",
      "motivation": [
        "supplementing",
        "commenting"
      ],
      "body": [
        {
          "type": "TextualBody",
          "value": " CHUCKLING",
          "format": "text/plain",
          "purpose": "commenting"
        },
        {
          "type": "TextualBody",
          "value": "Audience",
          "format": "text/plain",
          "purpose": "tagging"
        },
        {
          "type": "TextualBody",
          "value": "Session Discussion August 4",
          "format": "text/plain",
          "purpose": "tagging"
        }
      ],
      "target": {
        "source": "https://tanyaclement.github.io/harvard1953/august-4-afternoon-part-three/canvas-1/canvas",
        "selector": {
          "type": "PointSelector",
          "t": "1673.0"
        }
      }
    },
    {
      "@context": "http://www.w3.org/ns/anno.jsonld",
      "id": "august-4-afternoon-part-three-canvas-1-audience-annotation-17.json",
      "type": "Annotation",
      "motivation": [
        "supplementing",
        "commenting"
      ],
      "body": [
        {
          "type": "TextualBody",
          "value": " APPLAUSE",
          "format": "text/plain",
          "purpose": "commenting"
        },
        {
          "type": "TextualBody",
          "value": "Audience",
          "format": "text/plain",
          "purpose": "tagging"
        },
        {
          "type": "TextualBody",
          "value": "Session Discussion August 4",
          "format": "text/plain",
          "purpose": "tagging"
        }
      ],
      "target": {
        "source": "https://tanyaclement.github.io/harvard1953/august-4-afternoon-part-three/canvas-1/canvas",
        "selector": {
          "type": "PointSelector",
          "t": "1674.0"
        }
      }
    },
    {
      "@context": "http://www.w3.org/ns/anno.jsonld",
      "id": "august-4-afternoon-part-three-canvas-1-audience-annotation-18.json",
      "type": "Annotation",
      "motivation": [
        "supplementing",
        "commenting"
      ],
      "body": [
        {
          "type": "TextualBody",
          "value": " Seems to me that the most-- the very generalized discussion, which brought down INAUDIBLE , it was Ellison who said that the novel is a form of communication. And going from that, this question is directed to Mr. O'Connor, who has confused me considerably. I feel every time I stand up, there's a great chasm opening. And into this chasm disappear too many of my heroes.",
          "format": "text/plain",
          "purpose": "commenting"
        },
        {
          "type": "TextualBody",
          "value": "Audience",
          "format": "text/plain",
          "purpose": "tagging"
        },
        {
          "type": "TextualBody",
          "value": "Session Discussion August 4",
          "format": "text/plain",
          "purpose": "tagging"
        }
      ],
      "target": {
        "source": "https://tanyaclement.github.io/harvard1953/august-4-afternoon-part-three/canvas-1/canvas",
        "selector": {
          "type": "PointSelector",
          "t": "1702.0"
        }
      }
    },
    {
      "@context": "http://www.w3.org/ns/anno.jsonld",
      "id": "august-4-afternoon-part-three-canvas-1-audience-annotation-19.json",
      "type": "Annotation",
      "motivation": [
        "supplementing",
        "commenting"
      ],
      "body": [
        {
          "type": "TextualBody",
          "value": " CHUCKLING",
          "format": "text/plain",
          "purpose": "commenting"
        },
        {
          "type": "TextualBody",
          "value": "Audience",
          "format": "text/plain",
          "purpose": "tagging"
        },
        {
          "type": "TextualBody",
          "value": "Session Discussion August 4",
          "format": "text/plain",
          "purpose": "tagging"
        }
      ],
      "target": {
        "source": "https://tanyaclement.github.io/harvard1953/august-4-afternoon-part-three/canvas-1/canvas",
        "selector": {
          "type": "PointSelector",
          "t": "1730.0"
        }
      }
    },
    {
      "@context": "http://www.w3.org/ns/anno.jsonld",
      "id": "august-4-afternoon-part-three-canvas-1-audience-annotation-20.json",
      "type": "Annotation",
      "motivation": [
        "supplementing",
        "commenting"
      ],
      "body": [
        {
          "type": "TextualBody",
          "value": " Mr. O'Connor, spoke INAUDIBLE  of the novel of 1970-- '50 as emphasize middle-class values. And I think I got a pattern in my mind. This has been carried on.",
          "format": "text/plain",
          "purpose": "commenting"
        },
        {
          "type": "TextualBody",
          "value": "Audience",
          "format": "text/plain",
          "purpose": "tagging"
        },
        {
          "type": "TextualBody",
          "value": "Session Discussion August 4",
          "format": "text/plain",
          "purpose": "tagging"
        }
      ],
      "target": {
        "source": "https://tanyaclement.github.io/harvard1953/august-4-afternoon-part-three/canvas-1/canvas",
        "selector": {
          "type": "PointSelector",
          "t": "1732.0"
        }
      }
    },
    {
      "@context": "http://www.w3.org/ns/anno.jsonld",
      "id": "august-4-afternoon-part-three-canvas-1-audience-annotation-21.json",
      "type": "Annotation",
      "motivation": [
        "supplementing",
        "commenting"
      ],
      "body": [
        {
          "type": "TextualBody",
          "value": " In the '30s, we had the proletariat semi-political novels of Dos Passos and Steinbeck in dubious battle, which communicated the values of proletariat. And since the war, it seems to me we have a great many novelists who were in the war who are trying to communicate now the great uncertainty of the orgy of violence without reason that they were engulfed in. And I wonder if, Mr. O'Connor, do you think this is a valid thing for novels to communicate?",
          "format": "text/plain",
          "purpose": "commenting"
        },
        {
          "type": "TextualBody",
          "value": "Audience",
          "format": "text/plain",
          "purpose": "tagging"
        },
        {
          "type": "TextualBody",
          "value": "Session Discussion August 4",
          "format": "text/plain",
          "purpose": "tagging"
        }
      ],
      "target": {
        "source": "https://tanyaclement.github.io/harvard1953/august-4-afternoon-part-three/canvas-1/canvas",
        "selector": {
          "type": "PointSelector",
          "t": "1747.0"
        }
      }
    },
    {
      "@context": "http://www.w3.org/ns/anno.jsonld",
      "id": "august-4-afternoon-part-three-canvas-1-audience-annotation-22.json",
      "type": "Annotation",
      "motivation": [
        "supplementing",
        "commenting"
      ],
      "body": [
        {
          "type": "TextualBody",
          "value": " I know it's subjective. And is very personal to an individual. The novel has certainly become that, as you pointed out last night.",
          "format": "text/plain",
          "purpose": "commenting"
        },
        {
          "type": "TextualBody",
          "value": "Audience",
          "format": "text/plain",
          "purpose": "tagging"
        },
        {
          "type": "TextualBody",
          "value": "Session Discussion August 4",
          "format": "text/plain",
          "purpose": "tagging"
        }
      ],
      "target": {
        "source": "https://tanyaclement.github.io/harvard1953/august-4-afternoon-part-three/canvas-1/canvas",
        "selector": {
          "type": "PointSelector",
          "t": "1782.0"
        }
      }
    },
    {
      "@context": "http://www.w3.org/ns/anno.jsonld",
      "id": "august-4-afternoon-part-three-canvas-1-audience-annotation-23.json",
      "type": "Annotation",
      "motivation": [
        "supplementing",
        "commenting"
      ],
      "body": [
        {
          "type": "TextualBody",
          "value": " Yet isn't this all part of a pattern of communication, starting with the novel forebearers?",
          "format": "text/plain",
          "purpose": "commenting"
        },
        {
          "type": "TextualBody",
          "value": "Audience",
          "format": "text/plain",
          "purpose": "tagging"
        },
        {
          "type": "TextualBody",
          "value": "Session Discussion August 4",
          "format": "text/plain",
          "purpose": "tagging"
        }
      ],
      "target": {
        "source": "https://tanyaclement.github.io/harvard1953/august-4-afternoon-part-three/canvas-1/canvas",
        "selector": {
          "type": "PointSelector",
          "t": "1792.0"
        }
      }
    },
    {
      "@context": "http://www.w3.org/ns/anno.jsonld",
      "id": "august-4-afternoon-part-three-canvas-1-audience-annotation-24.json",
      "type": "Annotation",
      "motivation": [
        "supplementing",
        "commenting"
      ],
      "body": [
        {
          "type": "TextualBody",
          "value": " Mr. O'Connor?",
          "format": "text/plain",
          "purpose": "commenting"
        },
        {
          "type": "TextualBody",
          "value": "Audience",
          "format": "text/plain",
          "purpose": "tagging"
        },
        {
          "type": "TextualBody",
          "value": "Session Discussion August 4",
          "format": "text/plain",
          "purpose": "tagging"
        }
      ],
      "target": {
        "source": "https://tanyaclement.github.io/harvard1953/august-4-afternoon-part-three/canvas-1/canvas",
        "selector": {
          "type": "PointSelector",
          "t": "1801.0"
        }
      }
    }
  ]
}